{"nodes":[{"label":"CDZI","x":281.2403869628906,"y":-209.0797119140625,"id":"CDZI","attributes":{"Eccentricity":"4.0","Closeness Centrality":"0.4666666666666667","Degree":"2","Eigenvector Centrality":"0.5742876877877509","Betweenness Centrality":"1.0","industry":"Agric","Harmonic Closeness Centrality":"0.5833333333333334","Weighted Degree":"10.0"},"color":"rgb(255,50,12)","size":64.0},{"label":"ALCO","x":-0.2145521491765976,"y":-0.6245732307434082,"id":"ALCO","attributes":{"Eccentricity":"3.0","Closeness Centrality":"0.5833333333333334","Degree":"3","Eigenvector Centrality":"0.6912735903992938","Betweenness Centrality":"7.5","industry":"Agric","Harmonic Closeness Centrality":"0.6904761904761906","Weighted Degree":"11.0"},"color":"rgb(255,50,12)","size":70.0},{"label":"SERV","x":-344.04766845703125,"y":67.27674865722656,"id":"SERV","attributes":{"Eccentricity":"3.0","Closeness Centrality":"0.5","Degree":"2","Eigenvector Centrality":"0.6866991967241242","Betweenness Centrality":"0.0","industry":"Agric","Harmonic Closeness Centrality":"0.5952380952380951","Weighted Degree":"3.0"},"color":"rgb(255,50,12)","size":22.0},{"label":"CALM","x":-161.8502960205078,"y":310.5512390136719,"id":"CALM","attributes":{"Eccentricity":"2.0","Closeness Centrality":"0.7","Degree":"4","Eigenvector Centrality":"1.0","Betweenness Centrality":"13.0","industry":"Agric","Harmonic Closeness Centrality":"0.7857142857142857","Weighted Degree":"9.0"},"color":"rgb(255,50,12)","size":58.0},{"label":"GRIF","x":338.38714599609375,"y":89.2985610961914,"id":"GRIF","attributes":{"Eccentricity":"3.0","Closeness Centrality":"0.5","Degree":"2","Eigenvector Centrality":"0.4449042937649856","Betweenness Centrality":"6.0","industry":"Agric","Harmonic Closeness Centrality":"0.5952380952380951","Weighted Degree":"3.0"},"color":"rgb(255,50,12)","size":22.0},{"label":"BV","x":-266.61273193359375,"y":-227.17041015625,"id":"BV","attributes":{"Eccentricity":"4.0","Closeness Centrality":"0.35","Degree":"1","Eigenvector Centrality":"0.1719145426273005","Betweenness Centrality":"0.0","industry":"Agric","Harmonic Closeness Centrality":"0.42857142857142855","Weighted Degree":"1.0"},"color":"rgb(255,50,12)","size":10.0},{"label":"CTVA","x":11.608589172363281,"y":-350.61297607421875,"id":"CTVA","attributes":{"Eccentricity":"4.0","Closeness Centrality":"0.3888888888888889","Degree":"1","Eigenvector Centrality":"0.26177914648163547","Betweenness Centrality":"0.0","industry":"Agric","Harmonic Closeness Centrality":"0.46428571428571436","Weighted Degree":"1.0"},"color":"rgb(255,50,12)","size":10.0},{"label":"CVGW","x":141.48910522460938,"y":320.361083984375,"id":"CVGW","attributes":{"Eccentricity":"3.0","Closeness Centrality":"0.5384615384615384","Degree":"3","Eigenvector Centrality":"0.843203889504097","Betweenness Centrality":"2.5","industry":"Agric","Harmonic Closeness Centrality":"0.6666666666666666","Weighted Degree":"8.0"},"color":"rgb(255,50,12)","size":52.0}],"edges":[{"source":"CVGW","target":"CALM","id":"36834","attributes":{},"color":"rgb(255,50,12)","size":4.0},{"source":"GRIF","target":"BV","id":"36830","attributes":{},"color":"rgb(255,50,12)","size":1.0},{"source":"SERV","target":"CALM","id":"36833","attributes":{},"color":"rgb(255,50,12)","size":1.0},{"source":"CDZI","target":"ALCO","id":"36829","attributes":{},"color":"rgb(255,50,12)","size":8.0},{"source":"GRIF","target":"CALM","id":"36831","attributes":{},"color":"rgb(255,50,12)","size":2.0},{"source":"SERV","target":"CVGW","id":"36839","attributes":{},"color":"rgb(255,50,12)","size":2.0},{"source":"CALM","target":"ALCO","id":"36828","attributes":{},"color":"rgb(255,50,12)","size":2.0},{"source":"CTVA","target":"ALCO","id":"36827","attributes":{},"color":"rgb(255,50,12)","size":1.0},{"source":"CVGW","target":"CDZI","id":"36836","attributes":{},"color":"rgb(255,50,12)","size":2.0}]}