{"nodes": [{"label": "DJCO", "x": -415.10888671875, "y": -430.1300354003906, "id": "DJCO", "attributes": {"industry": "Books", "Centrality Measures": "", "Harmonic Closeness Centrality": 0.604, "Betweenness Centrality": 0.0, "Eigenvector Centrality": 0.429, "Closeness Centrality": 0.533, "Other Measures": "", "Eccentricity": 3.0, "Degree": 6.0, "Weighted Degree": 38.0}, "color": "rgb(0,244,241)", "size": 11.104116439819336}, {"label": "INWK", "x": -389.963134765625, "y": 447.8967590332031, "id": "INWK", "attributes": {"industry": "Books", "Centrality Measures": "", "Harmonic Closeness Centrality": 0.514, "Betweenness Centrality": 0.9, "Eigenvector Centrality": 0.108, "Closeness Centrality": 0.462, "Other Measures": "", "Eccentricity": 3.0, "Degree": 3.0, "Weighted Degree": 80.0}, "color": "rgb(0,244,241)", "size": 12.324455261230469}, {"label": "TRNC", "x": -226.3939971923828, "y": 245.00660705566406, "id": "TRNC", "attributes": {"industry": "Books", "Centrality Measures": "", "Harmonic Closeness Centrality": 0.792, "Betweenness Centrality": 6.945, "Eigenvector Centrality": 0.886, "Closeness Centrality": 0.706, "Other Measures": "", "Eccentricity": 2.0, "Degree": 14.0, "Weighted Degree": 917.0}, "color": "rgb(0,244,241)", "size": 36.644065856933594}, {"label": "ABTL", "x": 71.24853515625, "y": 594.6739501953125, "id": "ABTL", "attributes": {"industry": "Books", "Centrality Measures": "", "Harmonic Closeness Centrality": 0.514, "Betweenness Centrality": 0.45, "Eigenvector Centrality": 0.154, "Closeness Centrality": 0.462, "Other Measures": "", "Eccentricity": 3.0, "Degree": 3.0, "Weighted Degree": 17.0}, "color": "rgb(0,244,241)", "size": 10.49394702911377}, {"label": "LOAN", "x": 37.63566207885742, "y": -596.2471313476562, "id": "LOAN", "attributes": {"industry": "Books", "Centrality Measures": "", "Harmonic Closeness Centrality": 0.458, "Betweenness Centrality": 0.0, "Eigenvector Centrality": 0.07, "Closeness Centrality": 0.429, "Other Measures": "", "Eccentricity": 3.0, "Degree": 1.0, "Weighted Degree": 2.0}, "color": "rgb(0,244,241)", "size": 10.058111190795898}, {"label": "AUTO", "x": 498.4885559082031, "y": 331.05072021484375, "id": "AUTO", "attributes": {"industry": "Books", "Centrality Measures": "", "Harmonic Closeness Centrality": 0.0, "Betweenness Centrality": 0.0, "Eigenvector Centrality": 0.0, "Closeness Centrality": 0.0, "Other Measures": "", "Eccentricity": 0.0, "Degree": 0.0, "Weighted Degree": 0.0}, "color": "rgb(0,244,241)", "size": 10.0}, {"label": "VALU", "x": 485.8675842285156, "y": -368.3346252441406, "id": "VALU", "attributes": {"industry": "Books", "Centrality Measures": "", "Harmonic Closeness Centrality": 0.562, "Betweenness Centrality": 0.815, "Eigenvector Centrality": 0.224, "Closeness Centrality": 0.511, "Other Measures": "", "Eccentricity": 3.0, "Degree": 4.0, "Weighted Degree": 15.0}, "color": "rgb(0,244,241)", "size": 10.435834884643555}, {"label": "LEE", "x": 6.603537559509277, "y": 357.3897399902344, "id": "LEE", "attributes": {"industry": "Books", "Centrality Measures": "", "Harmonic Closeness Centrality": 0.854, "Betweenness Centrality": 21.203, "Eigenvector Centrality": 0.97, "Closeness Centrality": 0.774, "Other Measures": "", "Eccentricity": 2.0, "Degree": 17.0, "Weighted Degree": 631.0}, "color": "rgb(0,244,241)", "size": 28.334138870239258}, {"label": "WETF", "x": 275.5702819824219, "y": -256.4233093261719, "id": "WETF", "attributes": {"industry": "Books", "Centrality Measures": "", "Harmonic Closeness Centrality": 0.653, "Betweenness Centrality": 8.618, "Eigenvector Centrality": 0.432, "Closeness Centrality": 0.571, "Other Measures": "", "Eccentricity": 3.0, "Degree": 8.0, "Weighted Degree": 58.0}, "color": "rgb(0,244,241)", "size": 11.685230255126953}, {"label": "MNI", "x": -242.80130004882812, "y": -251.98037719726562, "id": "MNI", "attributes": {"industry": "Books", "Centrality Measures": "", "Harmonic Closeness Centrality": 0.771, "Betweenness Centrality": 12.621, "Eigenvector Centrality": 0.811, "Closeness Centrality": 0.686, "Other Measures": "", "Eccentricity": 2.0, "Degree": 13.0, "Weighted Degree": 1105.0}, "color": "rgb(0,244,241)", "size": 42.10654067993164}, {"label": "FOX", "x": 543.6597900390625, "y": -132.20582580566406, "id": "FOX", "attributes": {"industry": "Books", "Centrality Measures": "", "Harmonic Closeness Centrality": 0.66, "Betweenness Centrality": 1.959, "Eigenvector Centrality": 0.526, "Closeness Centrality": 0.585, "Other Measures": "", "Eccentricity": 3.0, "Degree": 8.0, "Weighted Degree": 55.0}, "color": "rgb(0,244,241)", "size": 11.598062515258789}, {"label": "FOXA", "x": -589.627197265625, "y": 4.422897815704346, "id": "FOXA", "attributes": {"industry": "Books", "Centrality Measures": "", "Harmonic Closeness Centrality": 0.812, "Betweenness Centrality": 31.082, "Eigenvector Centrality": 0.864, "Closeness Centrality": 0.727, "Other Measures": "", "Eccentricity": 2.0, "Degree": 15.0, "Weighted Degree": 397.0}, "color": "rgb(0,244,241)", "size": 21.53510856628418}, {"label": "TZOO", "x": 259.7267150878906, "y": -508.99603271484375, "id": "TZOO", "attributes": {"industry": "Books", "Centrality Measures": "", "Harmonic Closeness Centrality": 0.59, "Betweenness Centrality": 0.879, "Eigenvector Centrality": 0.373, "Closeness Centrality": 0.511, "Other Measures": "", "Eccentricity": 3.0, "Degree": 6.0, "Weighted Degree": 21.0}, "color": "rgb(0,244,241)", "size": 10.610169410705566}, {"label": "GHC", "x": -519.2191772460938, "y": -217.4108123779297, "id": "GHC", "attributes": {"industry": "Books", "Centrality Measures": "", "Harmonic Closeness Centrality": 0.688, "Betweenness Centrality": 2.213, "Eigenvector Centrality": 0.591, "Closeness Centrality": 0.615, "Other Measures": "", "Eccentricity": 2.0, "Degree": 9.0, "Weighted Degree": 80.0}, "color": "rgb(0,244,241)", "size": 12.324455261230469}, {"label": "SCHL", "x": -197.78744506835938, "y": -538.47119140625, "id": "SCHL", "attributes": {"industry": "Books", "Centrality Measures": "", "Harmonic Closeness Centrality": 0.667, "Betweenness Centrality": 2.729, "Eigenvector Centrality": 0.508, "Closeness Centrality": 0.6, "Other Measures": "", "Eccentricity": 2.0, "Degree": 8.0, "Weighted Degree": 65.0}, "color": "rgb(0,244,241)", "size": 11.888619422912598}, {"label": "MDP", "x": 318.33258056640625, "y": 19.64214324951172, "id": "MDP", "attributes": {"industry": "Books", "Centrality Measures": "", "Harmonic Closeness Centrality": 0.812, "Betweenness Centrality": 26.308, "Eigenvector Centrality": 0.885, "Closeness Centrality": 0.727, "Other Measures": "", "Eccentricity": 2.0, "Degree": 15.0, "Weighted Degree": 1577.0}, "color": "rgb(0,244,241)", "size": 55.820823669433594}, {"label": "LABL", "x": 576.0435180664062, "y": 100.39823913574219, "id": "LABL", "attributes": {"industry": "Books", "Centrality Measures": "", "Harmonic Closeness Centrality": 0.521, "Betweenness Centrality": 0.874, "Eigenvector Centrality": 0.113, "Closeness Centrality": 0.471, "Other Measures": "", "Eccentricity": 3.0, "Degree": 3.0, "Weighted Degree": 72.0}, "color": "rgb(0,244,241)", "size": 12.092009544372559}, {"label": "GCI", "x": -352.4167175292969, "y": 27.597248077392578, "id": "GCI", "attributes": {"industry": "Books", "Centrality Measures": "", "Harmonic Closeness Centrality": 0.854, "Betweenness Centrality": 17.666, "Eigenvector Centrality": 0.986, "Closeness Centrality": 0.774, "Other Measures": "", "Eccentricity": 2.0, "Degree": 17.0, "Weighted Degree": 882.0}, "color": "rgb(0,244,241)", "size": 35.62711715698242}, {"label": "NYT", "x": -0.555863082408905, "y": -341.2189636230469, "id": "NYT", "attributes": {"industry": "Books", "Centrality Measures": "", "Harmonic Closeness Centrality": 0.833, "Betweenness Centrality": 24.182, "Eigenvector Centrality": 0.95, "Closeness Centrality": 0.75, "Other Measures": "", "Eccentricity": 2.0, "Degree": 16.0, "Weighted Degree": 1298.0}, "color": "rgb(0,244,241)", "size": 47.71428680419922}, {"label": "SSP", "x": -175.52944946289062, "y": 541.090087890625, "id": "SSP", "attributes": {"industry": "Books", "Centrality Measures": "", "Harmonic Closeness Centrality": 0.75, "Betweenness Centrality": 3.662, "Eigenvector Centrality": 0.812, "Closeness Centrality": 0.667, "Other Measures": "", "Eccentricity": 2.0, "Degree": 12.0, "Weighted Degree": 113.0}, "color": "rgb(0,244,241)", "size": 13.283292770385742}, {"label": "TIME", "x": -135.9427490234375, "y": -45.44644546508789, "id": "TIME", "attributes": {"industry": "Books", "Centrality Measures": "", "Harmonic Closeness Centrality": 0.854, "Betweenness Centrality": 14.164, "Eigenvector Centrality": 1.0, "Closeness Centrality": 0.774, "Other Measures": "", "Eccentricity": 2.0, "Degree": 17.0, "Weighted Degree": 2065.0}, "color": "rgb(0,244,241)", "size": 70.0}, {"label": "AHC", "x": 259.7327575683594, "y": 254.15176391601562, "id": "AHC", "attributes": {"industry": "Books", "Centrality Measures": "", "Harmonic Closeness Centrality": 0.694, "Betweenness Centrality": 5.917, "Eigenvector Centrality": 0.64, "Closeness Centrality": 0.6, "Other Measures": "", "Eccentricity": 3.0, "Degree": 10.0, "Weighted Degree": 362.0}, "color": "rgb(0,244,241)", "size": 20.518159866333008}, {"label": "TST", "x": 99.0335922241211, "y": -113.03649139404297, "id": "TST", "attributes": {"industry": "Books", "Centrality Measures": "", "Harmonic Closeness Centrality": 0.632, "Betweenness Centrality": 2.265, "Eigenvector Centrality": 0.458, "Closeness Centrality": 0.558, "Other Measures": "", "Eccentricity": 3.0, "Degree": 7.0, "Weighted Degree": 38.0}, "color": "rgb(0,244,241)", "size": 11.104116439819336}, {"label": "JW", "x": -519.8215942382812, "y": 244.10340881347656, "id": "JW", "attributes": {"industry": "Books", "Centrality Measures": "", "Harmonic Closeness Centrality": 0.736, "Betweenness Centrality": 5.004, "Eigenvector Centrality": 0.751, "Closeness Centrality": 0.632, "Other Measures": "", "Eccentricity": 3.0, "Degree": 12.0, "Weighted Degree": 64.0}, "color": "rgb(0,244,241)", "size": 11.859563827514648}, {"label": "DLX", "x": 298.9634704589844, "y": 502.3681945800781, "id": "DLX", "attributes": {"industry": "Books", "Centrality Measures": "", "Harmonic Closeness Centrality": 0.604, "Betweenness Centrality": 5.903, "Eigenvector Centrality": 0.312, "Closeness Centrality": 0.533, "Other Measures": "", "Eccentricity": 3.0, "Degree": 6.0, "Weighted Degree": 86.0}, "color": "rgb(0,244,241)", "size": 12.498788833618164}, {"label": "NEWM", "x": 34.26115417480469, "y": 130.1094207763672, "id": "NEWM", "attributes": {"industry": "Books", "Centrality Measures": "", "Harmonic Closeness Centrality": 0.792, "Betweenness Centrality": 7.641, "Eigenvector Centrality": 0.885, "Closeness Centrality": 0.706, "Other Measures": "", "Eccentricity": 2.0, "Degree": 14.0, "Weighted Degree": 988.0}, "color": "rgb(0,244,241)", "size": 38.70702362060547}], "edges": [{"source": "MNI", "target": "LEE", "id": "48696", "attributes": {}, "color": "rgb(0,244,241)", "size": 68.0}, {"source": "TIME", "target": "NYT", "id": "48740", "attributes": {}, "color": "rgb(0,244,241)", "size": 96.0}, {"source": "LEE", "target": "GHC", "id": "48672", "attributes": {}, "color": "rgb(0,244,241)", "size": 28.0}, {"source": "MDP", "target": "FOXA", "id": "48637", "attributes": {}, "color": "rgb(0,244,241)", "size": 25.0}, {"source": "LEE", "target": "FOXA", "id": "48643", "attributes": {}, "color": "rgb(0,244,241)", "size": 8.0}, {"source": "SSP", "target": "MDP", "id": "48707", "attributes": {}, "color": "rgb(0,244,241)", "size": 11.0}, {"source": "TZOO", "target": "FOX", "id": "48635", "attributes": {}, "color": "rgb(0,244,241)", "size": 1.0}, {"source": "NYT", "target": "LEE", "id": "48691", "attributes": {}, "color": "rgb(0,244,241)", "size": 69.0}, {"source": "WETF", "target": "LEE", "id": "48681", "attributes": {}, "color": "rgb(0,244,241)", "size": 4.0}, {"source": "TRNC", "target": "MDP", "id": "48710", "attributes": {}, "color": "rgb(0,244,241)", "size": 11.0}, {"source": "NEWM", "target": "MNI", "id": "48723", "attributes": {}, "color": "rgb(0,244,241)", "size": 516.0}, {"source": "WETF", "target": "GHC", "id": "48667", "attributes": {}, "color": "rgb(0,244,241)", "size": 2.0}, {"source": "GCI", "target": "AHC", "id": "48607", "attributes": {}, "color": "rgb(0,244,241)", "size": 29.0}, {"source": "JW", "target": "TIME", "id": "48786", "attributes": {}, "color": "rgb(0,244,241)", "size": 10.0}, {"source": "TRNC", "target": "SSP", "id": "48772", "attributes": {}, "color": "rgb(0,244,241)", "size": 7.0}, {"source": "TRNC", "target": "NEWM", "id": "48729", "attributes": {}, "color": "rgb(0,244,241)", "size": 33.0}, {"source": "NYT", "target": "MDP", "id": "48700", "attributes": {}, "color": "rgb(0,244,241)", "size": 50.0}, {"source": "JW", "target": "SCHL", "id": "48753", "attributes": {}, "color": "rgb(0,244,241)", "size": 13.0}, {"source": "SCHL", "target": "GCI", "id": "48659", "attributes": {}, "color": "rgb(0,244,241)", "size": 6.0}, {"source": "TIME", "target": "LEE", "id": "48693", "attributes": {}, "color": "rgb(0,244,241)", "size": 35.0}, {"source": "TIME", "target": "DJCO", "id": "48618", "attributes": {}, "color": "rgb(0,244,241)", "size": 4.0}, {"source": "NYT", "target": "FOXA", "id": "48648", "attributes": {}, "color": "rgb(0,244,241)", "size": 127.0}, {"source": "TIME", "target": "MNI", "id": "48712", "attributes": {}, "color": "rgb(0,244,241)", "size": 61.0}, {"source": "SSP", "target": "NEWM", "id": "48725", "attributes": {}, "color": "rgb(0,244,241)", "size": 10.0}, {"source": "SCHL", "target": "MDP", "id": "48705", "attributes": {}, "color": "rgb(0,244,241)", "size": 4.0}, {"source": "JW", "target": "NYT", "id": "48748", "attributes": {}, "color": "rgb(0,244,241)", "size": 5.0}, {"source": "AHC", "target": "ABTL", "id": "48605", "attributes": {}, "color": "rgb(0,244,241)", "size": 4.0}, {"source": "TST", "target": "GCI", "id": "48665", "attributes": {}, "color": "rgb(0,244,241)", "size": 6.0}, {"source": "VALU", "target": "TST", "id": "48808", "attributes": {}, "color": "rgb(0,244,241)", "size": 4.0}, {"source": "WETF", "target": "ABTL", "id": "48606", "attributes": {}, "color": "rgb(0,244,241)", "size": 12.0}, {"source": "SSP", "target": "LEE", "id": "48694", "attributes": {}, "color": "rgb(0,244,241)", "size": 4.0}, {"source": "VALU", "target": "LEE", "id": "48695", "attributes": {}, "color": "rgb(0,244,241)", "size": 2.0}, {"source": "NEWM", "target": "FOXA", "id": "48639", "attributes": {}, "color": "rgb(0,244,241)", "size": 18.0}, {"source": "TZOO", "target": "TRNC", "id": "48789", "attributes": {}, "color": "rgb(0,244,241)", "size": 2.0}, {"source": "TRNC", "target": "FOX", "id": "48636", "attributes": {}, "color": "rgb(0,244,241)", "size": 3.0}, {"source": "TIME", "target": "SSP", "id": "48771", "attributes": {}, "color": "rgb(0,244,241)", "size": 5.0}, {"source": "TIME", "target": "GHC", "id": "48669", "attributes": {}, "color": "rgb(0,244,241)", "size": 2.0}, {"source": "JW", "target": "NEWM", "id": "48732", "attributes": {}, "color": "rgb(0,244,241)", "size": 1.0}, {"source": "INWK", "target": "DLX", "id": "48628", "attributes": {}, "color": "rgb(0,244,241)", "size": 42.0}, {"source": "GCI", "target": "DLX", "id": "48626", "attributes": {}, "color": "rgb(0,244,241)", "size": 2.0}, {"source": "MNI", "target": "FOXA", "id": "48640", "attributes": {}, "color": "rgb(0,244,241)", "size": 52.0}, {"source": "LEE", "target": "GCI", "id": "48661", "attributes": {}, "color": "rgb(0,244,241)", "size": 47.0}, {"source": "TST", "target": "NYT", "id": "48750", "attributes": {}, "color": "rgb(0,244,241)", "size": 10.0}, {"source": "GCI", "target": "FOX", "id": "48634", "attributes": {}, "color": "rgb(0,244,241)", "size": 1.0}, {"source": "NYT", "target": "AHC", "id": "48614", "attributes": {}, "color": "rgb(0,244,241)", "size": 96.0}, {"source": "SSP", "target": "FOXA", "id": "48644", "attributes": {}, "color": "rgb(0,244,241)", "size": 10.0}, {"source": "WETF", "target": "GCI", "id": "48663", "attributes": {}, "color": "rgb(0,244,241)", "size": 6.0}, {"source": "LEE", "target": "DLX", "id": "48625", "attributes": {}, "color": "rgb(0,244,241)", "size": 2.0}, {"source": "LEE", "target": "DJCO", "id": "48622", "attributes": {}, "color": "rgb(0,244,241)", "size": 4.0}, {"source": "LABL", "target": "INWK", "id": "48676", "attributes": {}, "color": "rgb(0,244,241)", "size": 36.0}, {"source": "FOXA", "target": "TZOO", "id": "48809", "attributes": {}, "color": "rgb(0,244,241)", "size": 1.0}, {"source": "SSP", "target": "MNI", "id": "48718", "attributes": {}, "color": "rgb(0,244,241)", "size": 13.0}, {"source": "TRNC", "target": "FOXA", "id": "48646", "attributes": {}, "color": "rgb(0,244,241)", "size": 7.0}, {"source": "NEWM", "target": "GHC", "id": "48668", "attributes": {}, "color": "rgb(0,244,241)", "size": 32.0}, {"source": "TIME", "target": "FOXA", "id": "48641", "attributes": {}, "color": "rgb(0,244,241)", "size": 96.0}, {"source": "TRNC", "target": "AHC", "id": "48609", "attributes": {}, "color": "rgb(0,244,241)", "size": 58.0}, {"source": "JW", "target": "SSP", "id": "48770", "attributes": {}, "color": "rgb(0,244,241)", "size": 2.0}, {"source": "VALU", "target": "MDP", "id": "48699", "attributes": {}, "color": "rgb(0,244,241)", "size": 6.0}, {"source": "JW", "target": "TST", "id": "48804", "attributes": {}, "color": "rgb(0,244,241)", "size": 4.0}, {"source": "LEE", "target": "AHC", "id": "48612", "attributes": {}, "color": "rgb(0,244,241)", "size": 110.0}, {"source": "GHC", "target": "FOXA", "id": "48642", "attributes": {}, "color": "rgb(0,244,241)", "size": 7.0}, {"source": "NYT", "target": "GHC", "id": "48673", "attributes": {}, "color": "rgb(0,244,241)", "size": 2.0}, {"source": "FOXA", "target": "SCHL", "id": "48759", "attributes": {}, "color": "rgb(0,244,241)", "size": 2.0}, {"source": "JW", "target": "DLX", "id": "48623", "attributes": {}, "color": "rgb(0,244,241)", "size": 2.0}, {"source": "WETF", "target": "SCHL", "id": "48760", "attributes": {}, "color": "rgb(0,244,241)", "size": 8.0}, {"source": "NYT", "target": "FOX", "id": "48631", "attributes": {}, "color": "rgb(0,244,241)", "size": 16.0}, {"source": "SSP", "target": "NYT", "id": "48746", "attributes": {}, "color": "rgb(0,244,241)", "size": 23.0}, {"source": "JW", "target": "MDP", "id": "48701", "attributes": {}, "color": "rgb(0,244,241)", "size": 10.0}, {"source": "MNI", "target": "AHC", "id": "48610", "attributes": {}, "color": "rgb(0,244,241)", "size": 27.0}, {"source": "TIME", "target": "AHC", "id": "48615", "attributes": {}, "color": "rgb(0,244,241)", "size": 4.0}, {"source": "MDP", "target": "FOX", "id": "48633", "attributes": {}, "color": "rgb(0,244,241)", "size": 7.0}, {"source": "LABL", "target": "DLX", "id": "48624", "attributes": {}, "color": "rgb(0,244,241)", "size": 34.0}, {"source": "NEWM", "target": "MDP", "id": "48706", "attributes": {}, "color": "rgb(0,244,241)", "size": 10.0}, {"source": "SSP", "target": "GCI", "id": "48658", "attributes": {}, "color": "rgb(0,244,241)", "size": 17.0}, {"source": "JW", "target": "GHC", "id": "48670", "attributes": {}, "color": "rgb(0,244,241)", "size": 2.0}, {"source": "MDP", "target": "GCI", "id": "48657", "attributes": {}, "color": "rgb(0,244,241)", "size": 19.0}, {"source": "SSP", "target": "AHC", "id": "48611", "attributes": {}, "color": "rgb(0,244,241)", "size": 6.0}, {"source": "TIME", "target": "MDP", "id": "48711", "attributes": {}, "color": "rgb(0,244,241)", "size": 1410.0}, {"source": "TIME", "target": "NEWM", "id": "48737", "attributes": {}, "color": "rgb(0,244,241)", "size": 76.0}, {"source": "WETF", "target": "TIME", "id": "48783", "attributes": {}, "color": "rgb(0,244,241)", "size": 2.0}, {"source": "ABTL", "target": "MNI", "id": "48716", "attributes": {}, "color": "rgb(0,244,241)", "size": 1.0}, {"source": "NYT", "target": "GCI", "id": "48660", "attributes": {}, "color": "rgb(0,244,241)", "size": 188.0}, {"source": "GCI", "target": "DJCO", "id": "48621", "attributes": {}, "color": "rgb(0,244,241)", "size": 4.0}, {"source": "JW", "target": "LEE", "id": "48692", "attributes": {}, "color": "rgb(0,244,241)", "size": 1.0}, {"source": "WETF", "target": "FOXA", "id": "48647", "attributes": {}, "color": "rgb(0,244,241)", "size": 21.0}, {"source": "DJCO", "target": "AHC", "id": "48608", "attributes": {}, "color": "rgb(0,244,241)", "size": 18.0}, {"source": "TRNC", "target": "TIME", "id": "48776", "attributes": {}, "color": "rgb(0,244,241)", "size": 46.0}, {"source": "NEWM", "target": "LEE", "id": "48690", "attributes": {}, "color": "rgb(0,244,241)", "size": 88.0}, {"source": "NYT", "target": "MNI", "id": "48713", "attributes": {}, "color": "rgb(0,244,241)", "size": 177.0}, {"source": "NEWM", "target": "AHC", "id": "48613", "attributes": {}, "color": "rgb(0,244,241)", "size": 10.0}, {"source": "TZOO", "target": "TIME", "id": "48784", "attributes": {}, "color": "rgb(0,244,241)", "size": 10.0}, {"source": "NYT", "target": "NEWM", "id": "48727", "attributes": {}, "color": "rgb(0,244,241)", "size": 107.0}, {"source": "TZOO", "target": "SCHL", "id": "48757", "attributes": {}, "color": "rgb(0,244,241)", "size": 2.0}, {"source": "NEWM", "target": "GCI", "id": "48656", "attributes": {}, "color": "rgb(0,244,241)", "size": 79.0}, {"source": "TST", "target": "LEE", "id": "48685", "attributes": {}, "color": "rgb(0,244,241)", "size": 2.0}, {"source": "TRNC", "target": "MNI", "id": "48720", "attributes": {}, "color": "rgb(0,244,241)", "size": 73.0}, {"source": "TRNC", "target": "NYT", "id": "48741", "attributes": {}, "color": "rgb(0,244,241)", "size": 324.0}, {"source": "MDP", "target": "LEE", "id": "48688", "attributes": {}, "color": "rgb(0,244,241)", "size": 3.0}, {"source": "NYT", "target": "LABL", "id": "48679", "attributes": {}, "color": "rgb(0,244,241)", "size": 2.0}, {"source": "GCI", "target": "FOXA", "id": "48649", "attributes": {}, "color": "rgb(0,244,241)", "size": 15.0}, {"source": "JW", "target": "GCI", "id": "48654", "attributes": {}, "color": "rgb(0,244,241)", "size": 10.0}, {"source": "GHC", "target": "FOX", "id": "48632", "attributes": {}, "color": "rgb(0,244,241)", "size": 3.0}, {"source": "TIME", "target": "FOX", "id": "48630", "attributes": {}, "color": "rgb(0,244,241)", "size": 21.0}, {"source": "JW", "target": "TRNC", "id": "48793", "attributes": {}, "color": "rgb(0,244,241)", "size": 4.0}, {"source": "MDP", "target": "INWK", "id": "48674", "attributes": {}, "color": "rgb(0,244,241)", "size": 2.0}, {"source": "MNI", "target": "GCI", "id": "48664", "attributes": {}, "color": "rgb(0,244,241)", "size": 103.0}, {"source": "MNI", "target": "MDP", "id": "48698", "attributes": {}, "color": "rgb(0,244,241)", "size": 7.0}, {"source": "TIME", "target": "SCHL", "id": "48756", "attributes": {}, "color": "rgb(0,244,241)", "size": 24.0}, {"source": "TZOO", "target": "SSP", "id": "48768", "attributes": {}, "color": "rgb(0,244,241)", "size": 5.0}, {"source": "NEWM", "target": "DJCO", "id": "48619", "attributes": {}, "color": "rgb(0,244,241)", "size": 4.0}, {"source": "LOAN", "target": "FOXA", "id": "48638", "attributes": {}, "color": "rgb(0,244,241)", "size": 2.0}, {"source": "TRNC", "target": "GCI", "id": "48650", "attributes": {}, "color": "rgb(0,244,241)", "size": 187.0}, {"source": "MDP", "target": "GHC", "id": "48666", "attributes": {}, "color": "rgb(0,244,241)", "size": 2.0}, {"source": "MNI", "target": "FOX", "id": "48629", "attributes": {}, "color": "rgb(0,244,241)", "size": 3.0}, {"source": "SCHL", "target": "NYT", "id": "48749", "attributes": {}, "color": "rgb(0,244,241)", "size": 6.0}, {"source": "MNI", "target": "DJCO", "id": "48617", "attributes": {}, "color": "rgb(0,244,241)", "size": 4.0}, {"source": "TRNC", "target": "LEE", "id": "48680", "attributes": {}, "color": "rgb(0,244,241)", "size": 156.0}, {"source": "TST", "target": "TRNC", "id": "48795", "attributes": {}, "color": "rgb(0,244,241)", "size": 6.0}, {"source": "TST", "target": "FOXA", "id": "48645", "attributes": {}, "color": "rgb(0,244,241)", "size": 6.0}, {"source": "VALU", "target": "WETF", "id": "48816", "attributes": {}, "color": "rgb(0,244,241)", "size": 3.0}, {"source": "TIME", "target": "GCI", "id": "48651", "attributes": {}, "color": "rgb(0,244,241)", "size": 163.0}, {"source": "NEWM", "target": "DLX", "id": "48627", "attributes": {}, "color": "rgb(0,244,241)", "size": 4.0}]}